08_sequential_circuits_behavioral/t_flip_flop/t_flip_flop_behavioral.v
module t_flip_flop_behavioral(clk, rst, t, q);
    input clk, rst, t;
    output reg q;

    always @(posedge clk or posedge rst) begin
        if (rst)
            q <= 1'b0;
        else if (t)
            q <= ~q;
        else
            q <= q;
    end
endmodule

behavioral_modeling/sequential_circuits/t_flip_flop_behavioral/t_flip_flop_behavioral_tb.v
module t_flip_flop_behavioral_tb;
    reg clk, rst, t;
    wire q;

    t_flip_flop_behavioral dut(clk, rst, t, q);

    initial begin
        clk = 0;
        forever #1 clk = ~clk;
    end

    initial begin
        $monitor("time=%0t clk=%b rst=%b t=%b q=%b", $time, clk, rst, t, q);

        rst=1; t=0; #3;
        rst=0; t=1; #6;
        t=0; #4;
        t=1; #6;

        $finish;
    end
    initial begin
	$dumpfile("wave.vcd");
	$dumpvars(0, t_flip_flop_behavioral_tb);
    end
  endmodule

behavioral_modeling/sequential_circuits/t_flip_flop_behavioral/wave.vcd
$date
	Wed Jul 08 14:38:04 2026
$end
$version
	Icarus Verilog
$end
$timescale
	1s
$end
$scope module t_flip_flop_behavioral_tb $end
$var wire 1 ! q $end
$var reg 1 " clk $end
$var reg 1 # rst $end
$var reg 1 $ t $end
$scope module dut $end
$var wire 1 " clk $end
$var wire 1 # rst $end
$var wire 1 $ t $end
$var reg 1 ! q $end
$upscope $end
$upscope $end
$enddefinitions $end
$comment Show the parameter values. $end
$dumpall
$end
#0
$dumpvars
0$
1#
0"
0!
$end
#1
1"
#2
0"
#3
1!
1"
1$
0#
#4
0"
#5
0!
1"
#6
0"
#7
1!
1"
#8
0"
#9
1"
0$
#10
0"
#11
1"
#12
0"
#13
0!
1"
1$
#14
0"
#15
1!
1"
#16
0"
#17
0!
1"
#18
0"
#19
1!
1"
